pydualsense/__init__.py
pydualsense/checksum.py
pydualsense/enums.py
pydualsense/event_system.py
pydualsense/hidapi.dll
pydualsense/hidguardian.py
pydualsense/pydualsense.py
pydualsense-0.7.5.dist-info/LICENSE
pydualsense-0.7.5.dist-info/METADATA
pydualsense-0.7.5.dist-info/WHEEL
pydualsense-0.7.5.dist-info/RECORD
