Metadata-Version: 2.3
Name: pydualsense
Version: 0.7.5
Summary: use your DualSense (PS5) controller with python
License: MIT
Keywords: ps5,controller,dualsense,pydualsense
Author: Florian (flok) K
Author-email: 37000563+flok@users.noreply.github.com
Requires-Python: >=3.8,<4.0
Classifier: License :: OSI Approved :: MIT License
Classifier: Programming Language :: Python :: 3
Classifier: Programming Language :: Python :: 3.8
Classifier: Programming Language :: Python :: 3.9
Classifier: Programming Language :: Python :: 3.10
Classifier: Programming Language :: Python :: 3.11
Classifier: Programming Language :: Python :: 3.12
Requires-Dist: hidapi-usb (>=0.3.2,<0.4.0)
Project-URL: Repository, https://github.com/flok/pydualsense
